pelican/plugins/pelican_bibtex_reader/__init__.py
pelican/plugins/pelican_bibtex_reader/bibtex.py
pelican/plugins/pelican_bibtex_reader/pelican_bibtex_reader.py
pelican/plugins/pelican_bibtex_reader/test_pelican_bibtex_reader.py
pelican_bibtex_reader-0.1.1.dist-info/LICENSE
pelican_bibtex_reader-0.1.1.dist-info/METADATA
pelican_bibtex_reader-0.1.1.dist-info/WHEEL
pelican_bibtex_reader-0.1.1.dist-info/RECORD
