Metadata-Version: 2.1
Name: pelican-bibtex-reader
Version: 0.1.1
Summary: A Pelican reader to process BibTeX files
Home-page: https://github.com/balanceofcowards/pelican-bibtex-reader
License: AGPL-3.0
Keywords: pelican,plugin,bibtex
Author: Andreas Fischer
Author-email: _@ndreas.de
Requires-Python: >=3.6.2,<4.0
Classifier: Development Status :: 3 - Alpha
Classifier: Environment :: Console
Classifier: Framework :: Pelican
Classifier: Framework :: Pelican :: Plugins
Classifier: Intended Audience :: End Users/Desktop
Classifier: License :: OSI Approved :: GNU Affero General Public License v3
Classifier: Operating System :: OS Independent
Classifier: Programming Language :: Python :: 3
Classifier: Programming Language :: Python :: 3.7
Classifier: Programming Language :: Python :: 3.8
Classifier: Programming Language :: Python :: 3.9
Classifier: Programming Language :: Python :: 3.10
Classifier: Programming Language :: Python :: 3.11
Classifier: Topic :: Internet :: WWW/HTTP
Classifier: Topic :: Software Development :: Libraries :: Python Modules
Provides-Extra: markdown
Requires-Dist: bibtexparser (>=1.0)
Requires-Dist: markdown (>=3.2) ; extra == "markdown"
Requires-Dist: pelican (>=4.5)
Project-URL: Documentation, https://docs.getpelican.com
Project-URL: Funding, https://donate.getpelican.com/
Project-URL: Issue Tracker, https://github.com/balanceofcowards/pelican-bibtex-reader/issues
Project-URL: Repository, https://github.com/balanceofcowards/pelican-bibtex-reader
